devhttp/AssetFile.py
devhttp/DevelopmentHttpServer.py
devhttp/DevelopmentRequestHandler.py
devhttp/LoadedAssetsModule.py
devhttp/ServerAssetsAccess.py
devhttp/__init__.py
devhttp/template_helpers.py
devhttp/utils.py
devhttp/endpoints/DynamicEndpoint.py
devhttp/endpoints/Endpoint.py
devhttp/endpoints/InternalError.py
devhttp/endpoints/NotFoundEndpoint.py
devhttp/endpoints/StaticEndpoint.py
devhttp/endpoints/__init__.py
devhttp-0.0.1.dist-info/LICENSE
devhttp-0.0.1.dist-info/METADATA
devhttp-0.0.1.dist-info/WHEEL
devhttp-0.0.1.dist-info/top_level.txt
devhttp-0.0.1.dist-info/RECORD
